ascend_utils/__init__.py
ascend_utils/common/__init__.py
ascend_utils/common/acl_inference.py
ascend_utils/common/hook.py
ascend_utils/common/mindspore_utils.py
ascend_utils/common/utils.py
ascend_utils/common/knowledge_distill/__init__.py
ascend_utils/common/knowledge_distill/utils.py
ascend_utils/common/prune/__init__.py
ascend_utils/common/prune/transformer_prune/__init__.py
ascend_utils/common/prune/transformer_prune/prune_utils_base.py
ascend_utils/common/prune/transformer_prune/prune_utils_ms.py
ascend_utils/common/prune/transformer_prune/prune_utils_torch.py
ascend_utils/common/security/__init__.py
ascend_utils/common/security/mindspore.py
ascend_utils/common/security/path.py
ascend_utils/common/security/pytorch.py
ascend_utils/common/security/type.py
ascend_utils/core/__init__.py
ascend_utils/core/dag/__init__.py
ascend_utils/core/dag/dag.py
ascend_utils/core/dag/dag_hook.py
ascend_utils/core/dag/dag_node.py
ascend_utils/core/dag/dag_node_io.py
ascend_utils/mindspore/__init__.py
ascend_utils/mindspore/dag/__init__.py
ascend_utils/mindspore/dag/dag_mindspore_hook.py
ascend_utils/mindspore/knowledge_distill/__init__.py
ascend_utils/mindspore/knowledge_distill/distill_dual_models_ms.py
ascend_utils/mindspore/knowledge_distill/distill_losses_func_ms.py
ascend_utils/mindspore/knowledge_distill/distill_losses_manager_ms.py
ascend_utils/mindspore/prune/__init__.py
ascend_utils/pytorch/__init__.py
ascend_utils/pytorch/dag/__init__.py
ascend_utils/pytorch/dag/dag_torch_hook.py
ascend_utils/pytorch/knowledge_distill/__init__.py
ascend_utils/pytorch/knowledge_distill/distill_dual_models_torch.py
ascend_utils/pytorch/knowledge_distill/distill_losses_func_torch.py
ascend_utils/pytorch/knowledge_distill/distill_losses_manager_torch.py
ascend_utils/pytorch/prune/__init__.py
config/__init__.py
lab_calib/__init__.py
lab_practice/__init__.py
modelslim/__init__.py
msitmodelslim/__init__.py
msmodelslim/__init__.py
msmodelslim/app/__init__.py
msmodelslim-8.2.1.dist-info/METADATA
msmodelslim-8.2.1.dist-info/WHEEL
msmodelslim-8.2.1.dist-info/entry_points.txt
msmodelslim-8.2.1.dist-info/top_level.txt
msmodelslim-8.2.1.dist-info/RECORD
