Metadata-Version: 2.4
Name: msmodelslim
Version: 8.2.1
Summary: msModelSlim, MindStudio ModelSlim Tools
Home-page: https://gitcode.com/Ascend/msit
License: Apache-2.0
Keywords: msmodelslim
Requires-Python: >=3.7
Requires-Dist: easydict==1.13
Requires-Dist: einops
Requires-Dist: pydantic>=2.10.1
Requires-Dist: wcmatch>=10.0
Dynamic: description-content-type
Dynamic: home-page
Dynamic: keywords
Dynamic: license
Dynamic: requires-dist
Dynamic: requires-python
Dynamic: summary
